{"chunk_definitions":[{"row":9,"row_count":1,"visible":true,"expansion_state":0,"options":{"engine":"r","label":"setup","include":false,"dev":"png"},"document_id":"A52FDFA6","chunk_id":"csetup_chunk","chunk_label":"setup"},{"row":85,"row_count":1,"visible":true,"expansion_state":0,"options":{"engine":"r","label":"unnamed-chunk-2","dev":"png"},"document_id":"A52FDFA6","chunk_id":"cfhewi3piyoa4","chunk_label":"unnamed-chunk-3"},{"row":117,"row_count":1,"visible":true,"expansion_state":0,"options":{"engine":"r","label":"unnamed-chunk-129","dev":"png"},"document_id":"A52FDFA6","chunk_id":"ccnxi7lx18050","chunk_label":"unnamed-chunk-4"}],"doc_write_time":1750818234,"chunk_rendered_width":577,"working_dir":null,"default_chunk_options":{"echo":true}}